khuauth/__init__.py
khuauth/auth.py
khuauth/auth_handler.py
khuauth/config.py
khuauth-0.0.2.dist-info/METADATA
khuauth-0.0.2.dist-info/WHEEL
khuauth-0.0.2.dist-info/top_level.txt
khuauth-0.0.2.dist-info/RECORD
