Metadata-Version: 2.1
Name: khuauth
Version: 0.0.2
Summary: A small example package
Home-page: UNKNOWN
Author: Jinsu Park
Author-email: bo314@naver.com
License: UNKNOWN
Platform: UNKNOWN
Classifier: Programming Language :: Python :: 3
Classifier: License :: OSI Approved :: MIT License
Classifier: Operating System :: OS Independent
Requires-Python: >=3.6
Requires-Dist: requests
Requires-Dist: beautifulsoup4
